PixelKing/__init__.py
PixelKing-1.0.0.dist-info/METADATA
PixelKing-1.0.0.dist-info/WHEEL
PixelKing-1.0.0.dist-info/top_level.txt
PixelKing-1.0.0.dist-info/RECORD
