Metadata-Version: 2.1
Name: PixelKing
Version: 1.0.0
Summary: Моудль для новичков
Author: ProgramKing_PixelSun
Author-email: vladgamer360@gmail.com
Classifier: Programming Language :: Python :: 3
Classifier: License :: OSI Approved :: MIT License
Classifier: Operating System :: OS Independent
Requires-Python: >=3.6
